rawjson/__init__.py
rawjson/exceptions/__init__.py
rawjson-0.1.8.1.dist-info/METADATA
rawjson-0.1.8.1.dist-info/WHEEL
rawjson-0.1.8.1.dist-info/top_level.txt
rawjson-0.1.8.1.dist-info/RECORD
