Metadata-Version: 2.1
Name: rawjson
Version: 0.1.8.1
Summary: /tellraw generator for Minecraft
Requires-Python: >=3.6
